concurrencytest.py
concurrencytest-0.1.4.dist-info/licenses/LICENSE
concurrencytest-0.1.4.dist-info/METADATA
concurrencytest-0.1.4.dist-info/WHEEL
concurrencytest-0.1.4.dist-info/top_level.txt
concurrencytest-0.1.4.dist-info/RECORD
